odoo/addons/rpc_helper/README.rst
odoo/addons/rpc_helper/__init__.py
odoo/addons/rpc_helper/__manifest__.py
odoo/addons/rpc_helper/decorator.py
odoo/addons/rpc_helper/hooks.py
odoo/addons/rpc_helper/patch.py
odoo/addons/rpc_helper/rpc_test_example.py
odoo/addons/rpc_helper/i18n/es.po
odoo/addons/rpc_helper/i18n/es_AR.po
odoo/addons/rpc_helper/i18n/it.po
odoo/addons/rpc_helper/i18n/rpc_helper.pot
odoo/addons/rpc_helper/models/__init__.py
odoo/addons/rpc_helper/models/ir_model.py
odoo/addons/rpc_helper/readme/CONFIGURE.md
odoo/addons/rpc_helper/readme/CONTRIBUTORS.md
odoo/addons/rpc_helper/readme/CREDITS.md
odoo/addons/rpc_helper/readme/DESCRIPTION.md
odoo/addons/rpc_helper/readme/USAGE.md
odoo/addons/rpc_helper/static/description/icon.png
odoo/addons/rpc_helper/static/description/index.html
odoo/addons/rpc_helper/tests/__init__.py
odoo/addons/rpc_helper/tests/test_decorator.py
odoo/addons/rpc_helper/tests/test_xmlrpc.py
odoo/addons/rpc_helper/views/ir_model_views.xml
odoo_addon_rpc_helper-18.0.1.0.1.2.dist-info/METADATA
odoo_addon_rpc_helper-18.0.1.0.1.2.dist-info/WHEEL
odoo_addon_rpc_helper-18.0.1.0.1.2.dist-info/top_level.txt
odoo_addon_rpc_helper-18.0.1.0.1.2.dist-info/RECORD
